eospyo/__init__.py
eospyo/_version.py
eospyo/exc.py
eospyo/net.py
eospyo/transaction.py
eospyo/types.py
eospyo/utils.py
eospyo-0.6.4.dist-info/LICENSE
eospyo-0.6.4.dist-info/WHEEL
eospyo-0.6.4.dist-info/METADATA
eospyo-0.6.4.dist-info/RECORD
